max31855/__init__.py
max31855/k_type_lin.py
max31855/max31855.py
pyMAX31855-0.0.1.dist-info/LICENSE
pyMAX31855-0.0.1.dist-info/METADATA
pyMAX31855-0.0.1.dist-info/WHEEL
pyMAX31855-0.0.1.dist-info/top_level.txt
pyMAX31855-0.0.1.dist-info/RECORD
