Metadata-Version: 2.1
Name: pyMAX31855
Version: 0.0.1
Summary: A python 3 interface for MAX31855 thermocouple IC
Home-page: https://github.com/menschel/pyMAX31855
Author: Patrick Menschel
Author-email: menschel.p@posteo.de
License: UNKNOWN
Keywords: temperature thermocouple max31855
Platform: UNKNOWN
Classifier: Development Status :: 4 - Beta
Classifier: Programming Language :: Python :: 3
Classifier: License :: OSI Approved :: GNU General Public License v3 or later (GPLv3+)
Classifier: Operating System :: OS Independent
Classifier: Intended Audience :: Science/Research
Classifier: Intended Audience :: Developers
Classifier: Topic :: Scientific/Engineering
Classifier: Topic :: Software Development :: Embedded Systems
Requires-Python: >=3.6
Requires-Dist: spidev
